Metadata-Version: 2.1
Name: plantfinder
Version: 0.0.1
Summary: A python package for finding rare plants in ArcGIS Pro. 
Home-page: https://github.com/jbeele16/plantfinder
Author: Jareth Beeler
Author-email: jbeele16@vols.utk.edu
License: MIT license
Keywords: plantfinder
Classifier: Development Status :: 2 - Pre-Alpha
Classifier: Intended Audience :: Developers
Classifier: License :: OSI Approved :: MIT License
Classifier: Natural Language :: English
Classifier: Programming Language :: Python :: 3
Classifier: Programming Language :: Python :: 3.7
Classifier: Programming Language :: Python :: 3.8
Classifier: Programming Language :: Python :: 3.9
Classifier: Programming Language :: Python :: 3.10
Requires-Python: >=3.7
License-File: LICENSE
